threadmsg/PROJECT.txt
threadmsg/__init__.py
threadmsg/threadmsg.py
threadmsg-0.2.4.dist-info/LICENSE
threadmsg-0.2.4.dist-info/METADATA
threadmsg-0.2.4.dist-info/WHEEL
threadmsg-0.2.4.dist-info/top_level.txt
threadmsg-0.2.4.dist-info/RECORD
