Metadata-Version: 2.1
Name: threadmsg
Version: 0.2.4
Summary: Thread safe message queue
Home-page: https://github.com/wheresjames/threadmsg
Author: Robert Umbehant
Author-email: threadmsg@wheresjames.com
License: MIT
Platform: UNKNOWN
